requestssmm/__init__.py
requestssmm/api.py
requestssmm/scrapt.py
requestssmm/utlites.py
requestssmm/smmv2/__init__.py
requestssmm/smmv2/api.py
requestssmm/smmv2/utlites.py
requestssmm-0.0.2.4.dist-info/licenses/LICENSE
requestssmm-0.0.2.4.dist-info/METADATA
requestssmm-0.0.2.4.dist-info/WHEEL
requestssmm-0.0.2.4.dist-info/top_level.txt
requestssmm-0.0.2.4.dist-info/RECORD
