Metadata-Version: 2.4
Name: requestssmm
Version: 0.0.2.4
License-File: LICENSE
Requires-Dist: requests
Requires-Dist: fb_atm
Requires-Dist: mahdix
Dynamic: license-file
Dynamic: requires-dist
